skinner/.DS_Store
skinner/__init__.py
skinner/agents.py
skinner/envs copy.py
skinner/envs.py
skinner/objects copy.py
skinner/objects.py
skinner/policies copy.py
skinner/policies.py
skinner/spaces.py
skinner/utils.py
skinner/worlds copy.py
skinner/worlds.py
skinner-0.2.1.dist-info/WHEEL
skinner-0.2.1.dist-info/METADATA
skinner-0.2.1.dist-info/RECORD
