Metadata-Version: 2.1
Name: skinner
Version: 0.2.1
Summary: 
Home-page: https://github.com/Freakwill/skinner
License: MIT
Keywords: gym,Reinforcement Learning,Artificial Intelligence
Author: William Song
Author-email: 30965609+Freakwill@users.noreply.github.com
Requires-Python: >=3.8,<4.0
Classifier: Environment :: MacOS X
Classifier: Intended Audience :: Science/Research
Classifier: License :: OSI Approved :: MIT License
Classifier: Operating System :: OS Independent
Classifier: Programming Language :: Python :: 3
Classifier: Programming Language :: Python :: 3.8
Classifier: Topic :: Scientific/Engineering :: Artificial Intelligence
Classifier: Topic :: Software Development :: Libraries :: Python Modules
Project-URL: Repository, https://github.com/Freakwill/skinner
